{"dataset": "wisconsin", "seed": 134600, "method": "selective_graph_correction", "selected_threshold_high": 0.05, "selected_weights": {"b1": 1.0, "b2": 0.6, "b3": 0.0, "b4": 0.5, "b5": 0.3}, "mode": "feature_first_selective_weighted_correction_v1", "feature_knn_used": false, "feature_knn_k": 5, "runtime_sec": {"mlp_training_runtime_sec": 0.0, "evidence_runtime_sec": 0.007459884014679119, "selection_runtime_sec": 0.0011300899786874652, "inference_runtime_sec": 5.913985660299659e-06, "selective_overhead_runtime_sec": 0.008595887979026884, "total_runtime_sec": 0.008595887979026884, "avg_runtime_overhead_over_mlp_sec": 0.008595887979026884}, "summary": {"val_acc_mlp": 0.8625, "val_acc_selective": 0.875, "test_acc_mlp": 0.9215686274509803, "test_acc_selective": 0.9215686274509803, "val_fraction_uncertain": 0.025, "test_fraction_uncertain": 0.0, "val_fraction_changed_from_mlp": 0.025, "test_fraction_changed_from_mlp": 0.0, "acc_val_confident": 0.8846153846153846, "acc_val_uncertain": 0.5, "acc_test_confident": 0.9215686274509803, "acc_test_uncertain": null}, "test_node_diagnostics": [{"node_id": 0, "mlp_pred": 1, "mlp_max_prob": 0.9084305763244629, "mlp_margin": 0.878547165542841, "was_uncertain": false, "final_pred": 1, "changed_from_mlp": false, "selected_threshold_high": 0.05, "selected_method_mode": "feature_first_selective_weighted_correction_v1", "winning_class_components": {"mlp_term": -0.09603680977904501, "feature_similarity_term": 0.3000007152557373, "feature_knn_term": 0.0, "graph_neighbor_term": 0.3282115790972645, "compatibility_term": 0.0932309180889204}}, {"node_id": 1, "mlp_pred": 2, "mlp_max_prob": 0.9955559372901917, "mlp_margin": 0.9936813018284738, "was_uncertain": false, "final_pred": 2, "changed_from_mlp": false, "selected_threshold_high": 0.05, "selected_method_mode": "feature_first_selective_weighted_correction_v1", "winning_class_components": {"mlp_term": -0.004453966910645215, "feature_similarity_term": 0.3000015735626221, "feature_knn_term": 0.0, "graph_neighbor_term": 0.0, "compatibility_term": 0.1617391304347826}}, {"node_id": 5, "mlp_pred": 1, "mlp_max_prob": 0.9999362230300903, "mlp_margin": 0.9999115601021913, "was_uncertain": false, "final_pred": 1, "changed_from_mlp": false, "selected_threshold_high": 0.05, "selected_method_mode": "feature_first_selective_weighted_correction_v1", "winning_class_components": {"mlp_term": -6.377900374708851e-05, "feature_similarity_term": 0.36467671394348145, "feature_knn_term": 0.0, "graph_neighbor_term": 0.05849077629892015, "compatibility_term": 0.1452297021678605}}, {"node_id": 11, "mlp_pred": 2, "mlp_max_prob": 0.9895849823951721, "mlp_margin": 0.9834403749555349, "was_uncertain": false, "final_pred": 2, "changed_from_mlp": false, "selected_threshold_high": 0.05, "selected_method_mode": "feature_first_selective_weighted_correction_v1", "winning_class_components": {"mlp_term": -0.010469633448299424, "feature_similarity_term": 0.30000150203704834, "feature_knn_term": 0.0, "graph_neighbor_term": 0.00035390287111227456, "compatibility_term": 0.13107929909844201}}, {"node_id": 20, "mlp_pred": 1, "mlp_max_prob": 0.9237964153289795, "mlp_margin": 0.8580618053674698, "was_uncertain": false, "final_pred": 1, "changed_from_mlp": false, "selected_threshold_high": 0.05, "selected_method_mode": "feature_first_selective_weighted_correction_v1", "winning_class_components": {"mlp_term": -0.07926356134715555, "feature_similarity_term": 0.3217383027076721, "feature_knn_term": 0.0, "graph_neighbor_term": 0.43148206828232744, "compatibility_term": 0.07976294601512106}}, {"node_id": 32, "mlp_pred": 2, "mlp_max_prob": 0.9935182929039001, "mlp_margin": 0.9898711568675935, "was_uncertain": false, "final_pred": 2, "changed_from_mlp": false, "selected_threshold_high": 0.05, "selected_method_mode": "feature_first_selective_weighted_correction_v1", "winning_class_components": {"mlp_term": -0.006502804574067845, "feature_similarity_term": 0.3000011086463928, "feature_knn_term": 0.0, "graph_neighbor_term": 0.0050522558105555926, "compatibility_term": 0.1603297532709961}}, {"node_id": 33, "mlp_pred": 2, "mlp_max_prob": 0.9957249164581299, "mlp_margin": 0.9939815688412637, "was_uncertain": false, "final_pred": 2, "changed_from_mlp": false, "selected_threshold_high": 0.05, "selected_method_mode": "feature_first_selective_weighted_correction_v1", "winning_class_components": {"mlp_term": -0.004284247839600299, "feature_similarity_term": 0.3000016093254089, "feature_knn_term": 0.0, "graph_neighbor_term": 0.005828410849600425, "compatibility_term": 0.16057063291522986}}, {"node_id": 34, "mlp_pred": 1, "mlp_max_prob": 0.8793267011642456, "mlp_margin": 0.8220684416592121, "was_uncertain": false, "final_pred": 1, "changed_from_mlp": false, "selected_threshold_high": 0.05, "selected_method_mode": "feature_first_selective_weighted_correction_v1", "winning_class_components": {"mlp_term": -0.12859877667105202, "feature_similarity_term": 0.3000008225440979, "feature_knn_term": 0.0, "graph_neighbor_term": 0.007650831676270406, "compatibility_term": 0.08608113339949235}}, {"node_id": 37, "mlp_pred": 3, "mlp_max_prob": 0.9554783701896667, "mlp_margin": 0.931404110044241, "was_uncertain": false, "final_pred": 3, "changed_from_mlp": false, "selected_threshold_high": 0.05, "selected_method_mode": "feature_first_selective_weighted_correction_v1", "winning_class_components": {"mlp_term": -0.04554315272217115, "feature_similarity_term": 0.3000011086463928, "feature_knn_term": 0.0, "graph_neighbor_term": 0.1408043924338835, "compatibility_term": 0.07426889971874548}}, {"node_id": 39, "mlp_pred": 2, "mlp_max_prob": 0.9960482716560364, "mlp_margin": 0.994010002585128, "was_uncertain": false, "final_pred": 2, "changed_from_mlp": false, "selected_threshold_high": 0.05, "selected_method_mode": "feature_first_selective_weighted_correction_v1", "winning_class_components": {"mlp_term": -0.003959557053845283, "feature_similarity_term": 0.4182767629623413, "feature_knn_term": 0.0, "graph_neighbor_term": 0.0, "compatibility_term": 0.02608695652173913}}, {"node_id": 50, "mlp_pred": 3, "mlp_max_prob": 0.41926565766334534, "mlp_margin": 0.13006198406219482, "was_uncertain": false, "final_pred": 3, "changed_from_mlp": false, "selected_threshold_high": 0.05, "selected_method_mode": "feature_first_selective_weighted_correction_v1", "winning_class_components": {"mlp_term": -0.8692505321345839, "feature_similarity_term": 0.30000053644180297, "feature_knn_term": 0.0, "graph_neighbor_term": 0.038684500741588086, "compatibility_term": 0.08169235835355255}}, {"node_id": 52, "mlp_pred": 1, "mlp_max_prob": 0.8281057476997375, "mlp_margin": 0.7762473858892918, "was_uncertain": false, "final_pred": 1, "changed_from_mlp": false, "selected_threshold_high": 0.05, "selected_method_mode": "feature_first_selective_weighted_correction_v1", "winning_class_components": {"mlp_term": -0.18861441813848465, "feature_similarity_term": 0.3000008940696716, "feature_knn_term": 0.0, "graph_neighbor_term": 0.05832936225528454, "compatibility_term": 0.14696403223059565}}, {"node_id": 53, "mlp_pred": 1, "mlp_max_prob": 0.9634348750114441, "mlp_margin": 0.9284644089639187, "was_uncertain": false, "final_pred": 1, "changed_from_mlp": false, "selected_threshold_high": 0.05, "selected_method_mode": "feature_first_selective_weighted_correction_v1", "winning_class_components": {"mlp_term": -0.03725038551237862, "feature_similarity_term": 0.3301690578460693, "feature_knn_term": 0.0, "graph_neighbor_term": 0.009771108815689808, "compatibility_term": 0.11707131763327791}}, {"node_id": 55, "mlp_pred": 2, "mlp_max_prob": 0.9997265934944153, "mlp_margin": 0.9996147185665905, "was_uncertain": false, "final_pred": 2, "changed_from_mlp": false, "selected_threshold_high": 0.05, "selected_method_mode": "feature_first_selective_weighted_correction_v1", "winning_class_components": {"mlp_term": -0.0002734438879572426, "feature_similarity_term": 0.30000189542770384, "feature_knn_term": 0.0, "graph_neighbor_term": 0.0, "compatibility_term": 0.1617391304347826}}, {"node_id": 62, "mlp_pred": 2, "mlp_max_prob": 0.9977641105651855, "mlp_margin": 0.9968536911765113, "was_uncertain": false, "final_pred": 2, "changed_from_mlp": false, "selected_threshold_high": 0.05, "selected_method_mode": "feature_first_selective_weighted_correction_v1", "winning_class_components": {"mlp_term": -0.0022383927677433317, "feature_similarity_term": 0.41871957778930663, "feature_knn_term": 0.0, "graph_neighbor_term": 0.0004947445595961538, "compatibility_term": 0.161538775222}}, {"node_id": 70, "mlp_pred": 2, "mlp_max_prob": 0.9931585192680359, "mlp_margin": 0.9908485021442175, "was_uncertain": false, "final_pred": 2, "changed_from_mlp": false, "selected_threshold_high": 0.05, "selected_method_mode": "feature_first_selective_weighted_correction_v1", "winning_class_components": {"mlp_term": -0.006864990952438899, "feature_similarity_term": 0.30000107288360595, "feature_knn_term": 0.0, "graph_neighbor_term": 0.015658639299481417, "compatibility_term": 0.14398376988870298}}, {"node_id": 72, "mlp_pred": 2, "mlp_max_prob": 0.7347383499145508, "mlp_margin": 0.5545869618654251, "was_uncertain": false, "final_pred": 2, "changed_from_mlp": false, "selected_threshold_high": 0.05, "selected_method_mode": "feature_first_selective_weighted_correction_v1", "winning_class_components": {"mlp_term": -0.30824082965835525, "feature_similarity_term": 0.30000035762786864, "feature_knn_term": 0.0, "graph_neighbor_term": 0.1446018435341233, "compatibility_term": 0.04317305072368683}}, {"node_id": 80, "mlp_pred": 2, "mlp_max_prob": 0.9888954162597656, "mlp_margin": 0.9807715360075235, "was_uncertain": false, "final_pred": 2, "changed_from_mlp": false, "selected_threshold_high": 0.05, "selected_method_mode": "feature_first_selective_weighted_correction_v1", "winning_class_components": {"mlp_term": -0.01116669990778729, "feature_similarity_term": 0.3000007152557373, "feature_knn_term": 0.0, "graph_neighbor_term": 0.0, "compatibility_term": 0.1617391304347826}}, {"node_id": 88, "mlp_pred": 2, "mlp_max_prob": 0.9967382550239563, "mlp_margin": 0.9945744755677879, "was_uncertain": false, "final_pred": 2, "changed_from_mlp": false, "selected_threshold_high": 0.05, "selected_method_mode": "feature_first_selective_weighted_correction_v1", "winning_class_components": {"mlp_term": -0.003267076061772591, "feature_similarity_term": 0.30000121593475343, "feature_knn_term": 0.0, "graph_neighbor_term": 0.0, "compatibility_term": 0.1617391304347826}}, {"node_id": 94, "mlp_pred": 2, "mlp_max_prob": 0.9998759031295776, "mlp_margin": 0.9998325990709418, "was_uncertain": false, "final_pred": 2, "changed_from_mlp": false, "selected_threshold_high": 0.05, "selected_method_mode": "feature_first_selective_weighted_correction_v1", "winning_class_components": {"mlp_term": -0.00012410457107607886, "feature_similarity_term": 0.41384096145629884, "feature_knn_term": 0.0, "graph_neighbor_term": 0.0, "compatibility_term": 0.1617391304347826}}, {"node_id": 99, "mlp_pred": 2, "mlp_max_prob": 0.9998635053634644, "mlp_margin": 0.9998157866466499, "was_uncertain": false, "final_pred": 2, "changed_from_mlp": false, "selected_threshold_high": 0.05, "selected_method_mode": "feature_first_selective_weighted_correction_v1", "winning_class_components": {"mlp_term": -0.00013650395277630027, "feature_similarity_term": 0.436397910118103, "feature_knn_term": 0.0, "graph_neighbor_term": 0.007470853091998609, "compatibility_term": 0.1560579337168303}}, {"node_id": 110, "mlp_pred": 1, "mlp_max_prob": 0.9943867921829224, "mlp_margin": 0.9924433788983151, "was_uncertain": false, "final_pred": 1, "changed_from_mlp": false, "selected_threshold_high": 0.05, "selected_method_mode": "feature_first_selective_weighted_correction_v1", "winning_class_components": {"mlp_term": -0.005629021071227841, "feature_similarity_term": 0.3311305046081543, "feature_knn_term": 0.0, "graph_neighbor_term": 0.004630732245468295, "compatibility_term": 0.14801168080955662}}, {"node_id": 116, "mlp_pred": 1, "mlp_max_prob": 0.9996987581253052, "mlp_margin": 0.9995455095195211, "was_uncertain": false, "final_pred": 1, "changed_from_mlp": false, "selected_threshold_high": 0.05, "selected_method_mode": "feature_first_selective_weighted_correction_v1", "winning_class_components": {"mlp_term": -0.00030128725714265034, "feature_similarity_term": 0.3857850909233093, "feature_knn_term": 0.0, "graph_neighbor_term": 0.46189820131939047, "compatibility_term": 0.07394931987078898}}, {"node_id": 118, "mlp_pred": 3, "mlp_max_prob": 0.9812615513801575, "mlp_margin": 0.973612304776907, "was_uncertain": false, "final_pred": 3, "changed_from_mlp": false, "selected_threshold_high": 0.05, "selected_method_mode": "feature_first_selective_weighted_correction_v1", "winning_class_components": {"mlp_term": -0.018916237847642726, "feature_similarity_term": 0.3000019669532776, "feature_knn_term": 0.0, "graph_neighbor_term": 0.2580540991960139, "compatibility_term": 0.045494880141011065}}, {"node_id": 119, "mlp_pred": 4, "mlp_max_prob": 0.9343512058258057, "mlp_margin": 0.9120445586740971, "was_uncertain": false, "final_pred": 4, "changed_from_mlp": false, "selected_threshold_high": 0.05, "selected_method_mode": "feature_first_selective_weighted_correction_v1", "winning_class_components": {"mlp_term": -0.0679028880642634, "feature_similarity_term": 0.30000096559524536, "feature_knn_term": 0.0, "graph_neighbor_term": 0.16666666666666666, "compatibility_term": 0.06666666666666667}}, {"node_id": 122, "mlp_pred": 2, "mlp_max_prob": 0.9979860782623291, "mlp_margin": 0.9968388414708897, "was_uncertain": false, "final_pred": 2, "changed_from_mlp": false, "selected_threshold_high": 0.05, "selected_method_mode": "feature_first_selective_weighted_correction_v1", "winning_class_components": {"mlp_term": -0.002015952404914956, "feature_similarity_term": 0.36541521549224854, "feature_knn_term": 0.0, "graph_neighbor_term": 0.12861794853516972, "compatibility_term": 0.04482197969305114}}, {"node_id": 135, "mlp_pred": 2, "mlp_max_prob": 0.9976020455360413, "mlp_margin": 0.9968243550974876, "was_uncertain": false, "final_pred": 2, "changed_from_mlp": false, "selected_threshold_high": 0.05, "selected_method_mode": "feature_first_selective_weighted_correction_v1", "winning_class_components": {"mlp_term": -0.0024008341612741495, "feature_similarity_term": 0.300001859664917, "feature_knn_term": 0.0, "graph_neighbor_term": 0.0723009200836746, "compatibility_term": 0.10245609195952556}}, {"node_id": 136, "mlp_pred": 2, "mlp_max_prob": 0.9800623059272766, "mlp_margin": 0.9662134069949389, "was_uncertain": false, "final_pred": 2, "changed_from_mlp": false, "selected_threshold_high": 0.05, "selected_method_mode": "feature_first_selective_weighted_correction_v1", "winning_class_components": {"mlp_term": -0.0201391318616687, "feature_similarity_term": 0.30000139474868776, "feature_knn_term": 0.0, "graph_neighbor_term": 0.00035776851862586096, "compatibility_term": 0.03913098548482526}}, {"node_id": 149, "mlp_pred": 1, "mlp_max_prob": 0.9964788556098938, "mlp_margin": 0.9944998773280531, "was_uncertain": false, "final_pred": 1, "changed_from_mlp": false, "selected_threshold_high": 0.05, "selected_method_mode": "feature_first_selective_weighted_correction_v1", "winning_class_components": {"mlp_term": -0.003527358209806597, "feature_similarity_term": 0.37431761026382443, "feature_knn_term": 0.0, "graph_neighbor_term": 0.2958076142616888, "compatibility_term": 0.09983927096529333}}, {"node_id": 158, "mlp_pred": 1, "mlp_max_prob": 0.9917687177658081, "mlp_margin": 0.9862391520291567, "was_uncertain": false, "final_pred": 1, "changed_from_mlp": false, "selected_threshold_high": 0.05, "selected_method_mode": "feature_first_selective_weighted_correction_v1", "winning_class_components": {"mlp_term": -0.008265346293847555, "feature_similarity_term": 0.30000118017196653, "feature_knn_term": 0.0, "graph_neighbor_term": 0.04813974876467675, "compatibility_term": 0.09353407771518028}}, {"node_id": 161, "mlp_pred": 3, "mlp_max_prob": 0.5213931798934937, "mlp_margin": 0.0781305730342865, "was_uncertain": false, "final_pred": 3, "changed_from_mlp": false, "selected_threshold_high": 0.05, "selected_method_mode": "feature_first_selective_weighted_correction_v1", "winning_class_components": {"mlp_term": -0.6512508579413309, "feature_similarity_term": 0.3000014305114746, "feature_knn_term": 0.0, "graph_neighbor_term": 0.1290319870396305, "compatibility_term": 0.0514274319147181}}, {"node_id": 162, "mlp_pred": 2, "mlp_max_prob": 0.99277663230896, "mlp_margin": 0.9883754961192608, "was_uncertain": false, "final_pred": 2, "changed_from_mlp": false, "selected_threshold_high": 0.05, "selected_method_mode": "feature_first_selective_weighted_correction_v1", "winning_class_components": {"mlp_term": -0.00724958252732469, "feature_similarity_term": 0.40220818519592283, "feature_knn_term": 0.0, "graph_neighbor_term": 0.0, "compatibility_term": 0.02608695652173913}}, {"node_id": 166, "mlp_pred": 2, "mlp_max_prob": 0.99754399061203, "mlp_margin": 0.9962040244136006, "was_uncertain": false, "final_pred": 2, "changed_from_mlp": false, "selected_threshold_high": 0.05, "selected_method_mode": "feature_first_selective_weighted_correction_v1", "winning_class_components": {"mlp_term": -0.0024590303263425464, "feature_similarity_term": 0.4066396951675415, "feature_knn_term": 0.0, "graph_neighbor_term": 0.0, "compatibility_term": 0.1617391304347826}}, {"node_id": 172, "mlp_pred": 2, "mlp_max_prob": 0.9919977784156799, "mlp_margin": 0.9882988552562892, "was_uncertain": false, "final_pred": 2, "changed_from_mlp": false, "selected_threshold_high": 0.05, "selected_method_mode": "feature_first_selective_weighted_correction_v1", "winning_class_components": {"mlp_term": -0.008034411200094594, "feature_similarity_term": 0.30000118017196653, "feature_knn_term": 0.0, "graph_neighbor_term": 0.0, "compatibility_term": 0.07565217391304348}}, {"node_id": 173, "mlp_pred": 3, "mlp_max_prob": 0.9452052712440491, "mlp_margin": 0.9068791158497334, "was_uncertain": false, "final_pred": 3, "changed_from_mlp": false, "selected_threshold_high": 0.05, "selected_method_mode": "feature_first_selective_weighted_correction_v1", "winning_class_components": {"mlp_term": -0.05635315682919105, "feature_similarity_term": 0.3000017523765564, "feature_knn_term": 0.0, "graph_neighbor_term": 0.08614922941136452, "compatibility_term": 0.08857199925686036}}, {"node_id": 176, "mlp_pred": 3, "mlp_max_prob": 0.8368862271308899, "mlp_margin": 0.6918815076351166, "was_uncertain": false, "final_pred": 3, "changed_from_mlp": false, "selected_threshold_high": 0.05, "selected_method_mode": "feature_first_selective_weighted_correction_v1", "winning_class_components": {"mlp_term": -0.17806714708566912, "feature_similarity_term": 0.3000005722045898, "feature_knn_term": 0.0, "graph_neighbor_term": 0.0002630851599202012, "compatibility_term": 0.11533351844281259}}, {"node_id": 179, "mlp_pred": 3, "mlp_max_prob": 0.6959912776947021, "mlp_margin": 0.5179730951786041, "was_uncertain": false, "final_pred": 3, "changed_from_mlp": false, "selected_threshold_high": 0.05, "selected_method_mode": "feature_first_selective_weighted_correction_v1", "winning_class_components": {"mlp_term": -0.3624181507740859, "feature_similarity_term": 0.30000135898590086, "feature_knn_term": 0.0, "graph_neighbor_term": 0.0004978262566447397, "compatibility_term": 0.11595778101763773}}, {"node_id": 185, "mlp_pred": 2, "mlp_max_prob": 0.9939849972724915, "mlp_margin": 0.9915791775565594, "was_uncertain": false, "final_pred": 2, "changed_from_mlp": false, "selected_threshold_high": 0.05, "selected_method_mode": "feature_first_selective_weighted_correction_v1", "winning_class_components": {"mlp_term": -0.006033165726699759, "feature_similarity_term": 0.3989704728126526, "feature_knn_term": 0.0, "graph_neighbor_term": 0.004146958509864336, "compatibility_term": 0.030380396006029042}}, {"node_id": 200, "mlp_pred": 1, "mlp_max_prob": 0.9983447790145874, "mlp_margin": 0.9972839771071449, "was_uncertain": false, "final_pred": 1, "changed_from_mlp": false, "selected_threshold_high": 0.05, "selected_method_mode": "feature_first_selective_weighted_correction_v1", "winning_class_components": {"mlp_term": -0.0016565923771810847, "feature_similarity_term": 0.36090524196624757, "feature_knn_term": 0.0, "graph_neighbor_term": 0.22710765613721348, "compatibility_term": 0.11305680467005305}}, {"node_id": 202, "mlp_pred": 2, "mlp_max_prob": 0.9442288279533386, "mlp_margin": 0.9011226445436478, "was_uncertain": false, "final_pred": 2, "changed_from_mlp": false, "selected_threshold_high": 0.05, "selected_method_mode": "feature_first_selective_weighted_correction_v1", "winning_class_components": {"mlp_term": -0.05738673971843029, "feature_similarity_term": 0.3511986494064331, "feature_knn_term": 0.0, "graph_neighbor_term": 0.02506247132801792, "compatibility_term": 0.1344777400594149}}, {"node_id": 204, "mlp_pred": 1, "mlp_max_prob": 0.8954258561134338, "mlp_margin": 0.8608830310404301, "was_uncertain": false, "final_pred": 1, "changed_from_mlp": false, "selected_threshold_high": 0.05, "selected_method_mode": "feature_first_selective_weighted_correction_v1", "winning_class_components": {"mlp_term": -0.1104558569857224, "feature_similarity_term": 0.30000092983245846, "feature_knn_term": 0.0, "graph_neighbor_term": 0.17262605757670094, "compatibility_term": 0.1261243181467821}}, {"node_id": 205, "mlp_pred": 1, "mlp_max_prob": 0.9982677698135376, "mlp_margin": 0.9977286795619875, "was_uncertain": false, "final_pred": 1, "changed_from_mlp": false, "selected_threshold_high": 0.05, "selected_method_mode": "feature_first_selective_weighted_correction_v1", "winning_class_components": {"mlp_term": -0.0017337322320149042, "feature_similarity_term": 0.3000017166137695, "feature_knn_term": 0.0, "graph_neighbor_term": 0.30858289606854267, "compatibility_term": 0.09757715203580324}}, {"node_id": 217, "mlp_pred": 1, "mlp_max_prob": 0.9999395608901978, "mlp_margin": 0.9999069222176331, "was_uncertain": false, "final_pred": 1, "changed_from_mlp": false, "selected_threshold_high": 0.05, "selected_method_mode": "feature_first_selective_weighted_correction_v1", "winning_class_components": {"mlp_term": -6.044093631883867e-05, "feature_similarity_term": 0.3000030755996704, "feature_knn_term": 0.0, "graph_neighbor_term": 0.12499244539889214, "compatibility_term": 0.10805041074749273}}, {"node_id": 221, "mlp_pred": 2, "mlp_max_prob": 0.925736129283905, "mlp_margin": 0.9006554614752531, "was_uncertain": false, "final_pred": 2, "changed_from_mlp": false, "selected_threshold_high": 0.05, "selected_method_mode": "feature_first_selective_weighted_correction_v1", "winning_class_components": {"mlp_term": -0.07716604252085896, "feature_similarity_term": 0.3390488147735596, "feature_knn_term": 0.0, "graph_neighbor_term": 0.0, "compatibility_term": 0.1617391304347826}}, {"node_id": 228, "mlp_pred": 1, "mlp_max_prob": 0.7807441353797913, "mlp_margin": 0.5747366547584534, "was_uncertain": false, "final_pred": 1, "changed_from_mlp": false, "selected_threshold_high": 0.05, "selected_method_mode": "feature_first_selective_weighted_correction_v1", "winning_class_components": {"mlp_term": -0.2475077943684015, "feature_similarity_term": 0.2845539093017578, "feature_knn_term": 0.0, "graph_neighbor_term": 0.0, "compatibility_term": 0.04830508474576271}}, {"node_id": 231, "mlp_pred": 4, "mlp_max_prob": 0.8821594715118408, "mlp_margin": 0.8176310136914253, "was_uncertain": false, "final_pred": 4, "changed_from_mlp": false, "selected_threshold_high": 0.05, "selected_method_mode": "feature_first_selective_weighted_correction_v1", "winning_class_components": {"mlp_term": -0.12538243261614027, "feature_similarity_term": 0.30000064373016355, "feature_knn_term": 0.0, "graph_neighbor_term": 0.035382714135398424, "compatibility_term": 0.07090918269346404}}, {"node_id": 236, "mlp_pred": 2, "mlp_max_prob": 0.9957477450370789, "mlp_margin": 0.9939131732098758, "was_uncertain": false, "final_pred": 2, "changed_from_mlp": false, "selected_threshold_high": 0.05, "selected_method_mode": "feature_first_selective_weighted_correction_v1", "winning_class_components": {"mlp_term": -0.0042613215103652945, "feature_similarity_term": 0.30000164508819577, "feature_knn_term": 0.0, "graph_neighbor_term": 1.2024524068509076e-05, "compatibility_term": 0.16172728778543402}}, {"node_id": 238, "mlp_pred": 2, "mlp_max_prob": 0.9576223492622375, "mlp_margin": 0.9345792904496193, "was_uncertain": false, "final_pred": 2, "changed_from_mlp": false, "selected_threshold_high": 0.05, "selected_method_mode": "feature_first_selective_weighted_correction_v1", "winning_class_components": {"mlp_term": -0.04330178618215101, "feature_similarity_term": 0.3000005006790161, "feature_knn_term": 0.0, "graph_neighbor_term": 0.15156821899481493, "compatibility_term": 0.08976079269203036}}, {"node_id": 239, "mlp_pred": 2, "mlp_max_prob": 0.9991195797920227, "mlp_margin": 0.9986807601235341, "was_uncertain": false, "final_pred": 2, "changed_from_mlp": false, "selected_threshold_high": 0.05, "selected_method_mode": "feature_first_selective_weighted_correction_v1", "winning_class_components": {"mlp_term": -0.0008808080054818163, "feature_similarity_term": 0.36905229091644287, "feature_knn_term": 0.0, "graph_neighbor_term": 0.0, "compatibility_term": 0.1617391304347826}}, {"node_id": 240, "mlp_pred": 3, "mlp_max_prob": 0.9172127842903137, "mlp_margin": 0.8731622770428658, "was_uncertain": false, "final_pred": 3, "changed_from_mlp": false, "selected_threshold_high": 0.05, "selected_method_mode": "feature_first_selective_weighted_correction_v1", "winning_class_components": {"mlp_term": -0.08641578970661015, "feature_similarity_term": 0.3000012874603271, "feature_knn_term": 0.0, "graph_neighbor_term": 0.09560569322329558, "compatibility_term": 0.07309073140410069}}, {"node_id": 242, "mlp_pred": 1, "mlp_max_prob": 0.850173830986023, "mlp_margin": 0.8017674870789051, "was_uncertain": false, "final_pred": 1, "changed_from_mlp": false, "selected_threshold_high": 0.05, "selected_method_mode": "feature_first_selective_weighted_correction_v1", "winning_class_components": {"mlp_term": -0.16231444336410955, "feature_similarity_term": 0.30000067949295045, "feature_knn_term": 0.0, "graph_neighbor_term": 0.37578497688529644, "compatibility_term": 0.09059275140986088}}]}