{"dataset": "texas", "seed": 133700, "method": "selective_graph_correction", "selected_threshold_high": 0.05, "selected_weights": {"b1": 1.0, "b2": 0.6, "b3": 0.0, "b4": 0.5, "b5": 0.3}, "mode": "feature_first_selective_weighted_correction_v1", "feature_knn_used": false, "feature_knn_k": 5, "runtime_sec": {"mlp_training_runtime_sec": 0.0, "evidence_runtime_sec": 0.009135394939221442, "selection_runtime_sec": 0.002242229995317757, "inference_runtime_sec": 1.099100336432457e-05, "selective_overhead_runtime_sec": 0.011388615937903523, "total_runtime_sec": 0.011388615937903523, "avg_runtime_overhead_over_mlp_sec": 0.011388615937903523}, "summary": {"val_acc_mlp": 0.8135593220338984, "val_acc_selective": 0.8135593220338984, "test_acc_mlp": 0.7567567567567568, "test_acc_selective": 0.7567567567567568, "val_fraction_uncertain": 0.03389830508474576, "test_fraction_uncertain": 0.05405405405405406, "val_fraction_changed_from_mlp": 0.0, "test_fraction_changed_from_mlp": 0.05405405405405406, "acc_val_confident": 0.8245614035087719, "acc_val_uncertain": 0.5, "acc_test_confident": 0.8, "acc_test_uncertain": 0.0}, "test_node_diagnostics": [{"node_id": 10, "mlp_pred": 3, "mlp_max_prob": 0.9983445405960083, "mlp_margin": 0.9977001087972894, "was_uncertain": false, "final_pred": 3, "changed_from_mlp": false, "selected_threshold_high": 0.05, "selected_method_mode": "feature_first_selective_weighted_correction_v1", "winning_class_components": {"mlp_term": -0.0016568311910784294, "feature_similarity_term": 0.3765111923217773, "feature_knn_term": 0.0, "graph_neighbor_term": 0.0, "compatibility_term": 0.09056603773584905}}, {"node_id": 14, "mlp_pred": 3, "mlp_max_prob": 0.8181484937667847, "mlp_margin": 0.7471790984272957, "was_uncertain": false, "final_pred": 3, "changed_from_mlp": false, "selected_threshold_high": 0.05, "selected_method_mode": "feature_first_selective_weighted_correction_v1", "winning_class_components": {"mlp_term": -0.20071142613223017, "feature_similarity_term": 0.299999874830246, "feature_knn_term": 0.0, "graph_neighbor_term": 0.0026268953856686365, "compatibility_term": 0.05151729179956443}}, {"node_id": 17, "mlp_pred": 3, "mlp_max_prob": 0.9077890515327454, "mlp_margin": 0.8585119284689426, "was_uncertain": false, "final_pred": 3, "changed_from_mlp": false, "selected_threshold_high": 0.05, "selected_method_mode": "feature_first_selective_weighted_correction_v1", "winning_class_components": {"mlp_term": -0.09674324947230413, "feature_similarity_term": 0.3427670359611511, "feature_knn_term": 0.0, "graph_neighbor_term": 0.09297968568440117, "compatibility_term": 0.06959924069571741}}, {"node_id": 20, "mlp_pred": 0, "mlp_max_prob": 0.9885741472244263, "mlp_margin": 0.9811282134614885, "was_uncertain": false, "final_pred": 0, "changed_from_mlp": false, "selected_threshold_high": 0.05, "selected_method_mode": "feature_first_selective_weighted_correction_v1", "winning_class_components": {"mlp_term": -0.011491629347004454, "feature_similarity_term": 0.3000008583068848, "feature_knn_term": 0.0, "graph_neighbor_term": 0.04091593141685215, "compatibility_term": 0.09493500103466389}}, {"node_id": 22, "mlp_pred": 3, "mlp_max_prob": 0.6759024858474731, "mlp_margin": 0.5320312976837158, "was_uncertain": false, "final_pred": 3, "changed_from_mlp": false, "selected_threshold_high": 0.05, "selected_method_mode": "feature_first_selective_weighted_correction_v1", "winning_class_components": {"mlp_term": -0.3917064650493722, "feature_similarity_term": 0.3349136710166931, "feature_knn_term": 0.0, "graph_neighbor_term": 0.14809293093822562, "compatibility_term": 0.06561554392640997}}, {"node_id": 29, "mlp_pred": 0, "mlp_max_prob": 0.413179486989975, "mlp_margin": 0.10733658075332642, "was_uncertain": false, "final_pred": 0, "changed_from_mlp": false, "selected_threshold_high": 0.05, "selected_method_mode": "feature_first_selective_weighted_correction_v1", "winning_class_components": {"mlp_term": -0.8838731872333102, "feature_similarity_term": 0.3000004649162292, "feature_knn_term": 0.0, "graph_neighbor_term": 0.022171194997561896, "compatibility_term": 0.09744841166962119}}, {"node_id": 30, "mlp_pred": 3, "mlp_max_prob": 0.9697946310043335, "mlp_margin": 0.9562716027721763, "was_uncertain": false, "final_pred": 3, "changed_from_mlp": false, "selected_threshold_high": 0.05, "selected_method_mode": "feature_first_selective_weighted_correction_v1", "winning_class_components": {"mlp_term": -0.030670950514770944, "feature_similarity_term": 0.33303773403167725, "feature_knn_term": 0.0, "graph_neighbor_term": 0.20605199303125704, "compatibility_term": 0.07446540335603283}}, {"node_id": 31, "mlp_pred": 3, "mlp_max_prob": 0.9466015696525574, "mlp_margin": 0.9149534218013287, "was_uncertain": false, "final_pred": 3, "changed_from_mlp": false, "selected_threshold_high": 0.05, "selected_method_mode": "feature_first_selective_weighted_correction_v1", "winning_class_components": {"mlp_term": -0.05487700331090221, "feature_similarity_term": 0.3000005006790161, "feature_knn_term": 0.0, "graph_neighbor_term": 0.13880181408926384, "compatibility_term": 0.07121791336078567}}, {"node_id": 49, "mlp_pred": 3, "mlp_max_prob": 0.6449838280677795, "mlp_margin": 0.4615311920642853, "was_uncertain": false, "final_pred": 3, "changed_from_mlp": false, "selected_threshold_high": 0.05, "selected_method_mode": "feature_first_selective_weighted_correction_v1", "winning_class_components": {"mlp_term": -0.43853003526382406, "feature_similarity_term": 0.3000004649162292, "feature_knn_term": 0.0, "graph_neighbor_term": 0.06303634981551098, "compatibility_term": 0.06172536601177444}}, {"node_id": 51, "mlp_pred": 2, "mlp_max_prob": 0.8811979293823242, "mlp_margin": 0.8282936997711658, "was_uncertain": false, "final_pred": 2, "changed_from_mlp": false, "selected_threshold_high": 0.05, "selected_method_mode": "feature_first_selective_weighted_correction_v1", "winning_class_components": {"mlp_term": -0.1264730138271089, "feature_similarity_term": 0.3293456196784973, "feature_knn_term": 0.0, "graph_neighbor_term": 0.0, "compatibility_term": 0.1714285714285714}}, {"node_id": 54, "mlp_pred": 3, "mlp_max_prob": 0.9370389580726624, "mlp_margin": 0.8893632777035236, "was_uncertain": false, "final_pred": 3, "changed_from_mlp": false, "selected_threshold_high": 0.05, "selected_method_mode": "feature_first_selective_weighted_correction_v1", "winning_class_components": {"mlp_term": -0.06503042015588552, "feature_similarity_term": 0.30000014305114747, "feature_knn_term": 0.0, "graph_neighbor_term": 0.0544998026695051, "compatibility_term": 0.08084028614802645}}, {"node_id": 56, "mlp_pred": 2, "mlp_max_prob": 0.3197817802429199, "mlp_margin": 0.08802366256713867, "was_uncertain": false, "final_pred": 2, "changed_from_mlp": false, "selected_threshold_high": 0.05, "selected_method_mode": "feature_first_selective_weighted_correction_v1", "winning_class_components": {"mlp_term": -1.1401164525538623, "feature_similarity_term": 0.30893683433532715, "feature_knn_term": 0.0, "graph_neighbor_term": 0.0280026962497496, "compatibility_term": 0.12862681564195944}}, {"node_id": 57, "mlp_pred": 3, "mlp_max_prob": 0.9667442440986633, "mlp_margin": 0.9480728581547737, "was_uncertain": false, "final_pred": 3, "changed_from_mlp": false, "selected_threshold_high": 0.05, "selected_method_mode": "feature_first_selective_weighted_correction_v1", "winning_class_components": {"mlp_term": -0.0338213023798836, "feature_similarity_term": 0.3000001072883606, "feature_knn_term": 0.0, "graph_neighbor_term": 0.3682189540547789, "compatibility_term": 0.08929229521108528}}, {"node_id": 68, "mlp_pred": 3, "mlp_max_prob": 0.9866601228713989, "mlp_margin": 0.9819293348118663, "was_uncertain": false, "final_pred": 3, "changed_from_mlp": false, "selected_threshold_high": 0.05, "selected_method_mode": "feature_first_selective_weighted_correction_v1", "winning_class_components": {"mlp_term": -0.01342965257906751, "feature_similarity_term": 0.3000008940696716, "feature_knn_term": 0.0, "graph_neighbor_term": 0.0544998026695051, "compatibility_term": 0.061028964876689004}}, {"node_id": 79, "mlp_pred": 3, "mlp_max_prob": 0.9775274991989136, "mlp_margin": 0.9670231640338898, "was_uncertain": false, "final_pred": 3, "changed_from_mlp": false, "selected_threshold_high": 0.05, "selected_method_mode": "feature_first_selective_weighted_correction_v1", "winning_class_components": {"mlp_term": -0.022728855345516757, "feature_similarity_term": 0.32805676460266114, "feature_knn_term": 0.0, "graph_neighbor_term": 0.050382247463749565, "compatibility_term": 0.06372076747587636}}, {"node_id": 80, "mlp_pred": 4, "mlp_max_prob": 0.9125109314918518, "mlp_margin": 0.8695895373821259, "was_uncertain": false, "final_pred": 4, "changed_from_mlp": false, "selected_threshold_high": 0.05, "selected_method_mode": "feature_first_selective_weighted_correction_v1", "winning_class_components": {"mlp_term": -0.09155521388014885, "feature_similarity_term": 0.30000014305114747, "feature_knn_term": 0.0, "graph_neighbor_term": 0.020604095339627836, "compatibility_term": 0.08370699103350888}}, {"node_id": 81, "mlp_pred": 3, "mlp_max_prob": 0.9990372657775879, "mlp_margin": 0.998638337070588, "was_uncertain": false, "final_pred": 3, "changed_from_mlp": false, "selected_threshold_high": 0.05, "selected_method_mode": "feature_first_selective_weighted_correction_v1", "winning_class_components": {"mlp_term": -0.0009631979486575858, "feature_similarity_term": 0.30000146627426144, "feature_knn_term": 0.0, "graph_neighbor_term": 0.0544998026695051, "compatibility_term": 0.08084028614802645}}, {"node_id": 84, "mlp_pred": 3, "mlp_max_prob": 0.307784765958786, "mlp_margin": 0.006237834692001343, "was_uncertain": true, "final_pred": 4, "changed_from_mlp": true, "selected_threshold_high": 0.05, "selected_method_mode": "feature_first_selective_weighted_correction_v1", "winning_class_components": {"mlp_term": -1.1988296156688918, "feature_similarity_term": 0.30000064373016355, "feature_knn_term": 0.0, "graph_neighbor_term": 0.22225614608480604, "compatibility_term": 0.057345950654909716}}, {"node_id": 90, "mlp_pred": 3, "mlp_max_prob": 0.8449253439903259, "mlp_margin": 0.7536773681640625, "was_uncertain": false, "final_pred": 3, "changed_from_mlp": false, "selected_threshold_high": 0.05, "selected_method_mode": "feature_first_selective_weighted_correction_v1", "winning_class_components": {"mlp_term": -0.1685070058353881, "feature_similarity_term": 0.30000007152557373, "feature_knn_term": 0.0, "graph_neighbor_term": 0.1771540940270723, "compatibility_term": 0.085084007633761}}, {"node_id": 97, "mlp_pred": 3, "mlp_max_prob": 0.933474600315094, "mlp_margin": 0.9110655803233385, "was_uncertain": false, "final_pred": 3, "changed_from_mlp": false, "selected_threshold_high": 0.05, "selected_method_mode": "feature_first_selective_weighted_correction_v1", "winning_class_components": {"mlp_term": -0.06884152545988136, "feature_similarity_term": 0.3000010013580322, "feature_knn_term": 0.0, "graph_neighbor_term": 0.09297968568440117, "compatibility_term": 0.06959924069571741}}, {"node_id": 99, "mlp_pred": 4, "mlp_max_prob": 0.9756223559379578, "mlp_margin": 0.9633692894130945, "was_uncertain": false, "final_pred": 4, "changed_from_mlp": false, "selected_threshold_high": 0.05, "selected_method_mode": "feature_first_selective_weighted_correction_v1", "winning_class_components": {"mlp_term": -0.024679697837360574, "feature_similarity_term": 0.30000075101852414, "feature_knn_term": 0.0, "graph_neighbor_term": 0.03678867012736228, "compatibility_term": 0.07098490410591655}}, {"node_id": 102, "mlp_pred": 4, "mlp_max_prob": 0.6032354831695557, "mlp_margin": 0.262111634016037, "was_uncertain": false, "final_pred": 4, "changed_from_mlp": false, "selected_threshold_high": 0.05, "selected_method_mode": "feature_first_selective_weighted_correction_v1", "winning_class_components": {"mlp_term": -0.5054476391352907, "feature_similarity_term": 0.30083523988723754, "feature_knn_term": 0.0, "graph_neighbor_term": 0.07540443478171825, "compatibility_term": 0.0843813943298441}}, {"node_id": 117, "mlp_pred": 4, "mlp_max_prob": 0.9317250847816467, "mlp_margin": 0.8980474136769772, "was_uncertain": false, "final_pred": 4, "changed_from_mlp": false, "selected_threshold_high": 0.05, "selected_method_mode": "feature_first_selective_weighted_correction_v1", "winning_class_components": {"mlp_term": -0.07071748122000958, "feature_similarity_term": 0.3000006079673767, "feature_knn_term": 0.0, "graph_neighbor_term": 0.04068033875809003, "compatibility_term": 0.06956747369220835}}, {"node_id": 129, "mlp_pred": 3, "mlp_max_prob": 0.4450148344039917, "mlp_margin": 0.12338721752166748, "was_uncertain": false, "final_pred": 3, "changed_from_mlp": false, "selected_threshold_high": 0.05, "selected_method_mode": "feature_first_selective_weighted_correction_v1", "winning_class_components": {"mlp_term": -0.809647661632213, "feature_similarity_term": 0.2999997854232788, "feature_knn_term": 0.0, "graph_neighbor_term": 0.08750435008359128, "compatibility_term": 0.06481868007417275}}, {"node_id": 132, "mlp_pred": 3, "mlp_max_prob": 0.5971695780754089, "mlp_margin": 0.3869418799877167, "was_uncertain": false, "final_pred": 3, "changed_from_mlp": false, "selected_threshold_high": 0.05, "selected_method_mode": "feature_first_selective_weighted_correction_v1", "winning_class_components": {"mlp_term": -0.5155541555466362, "feature_similarity_term": 0.3000007152557373, "feature_knn_term": 0.0, "graph_neighbor_term": 0.05756306870377826, "compatibility_term": 0.058558617340153975}}, {"node_id": 136, "mlp_pred": 3, "mlp_max_prob": 0.8293383121490479, "mlp_margin": 0.7406101152300835, "was_uncertain": false, "final_pred": 3, "changed_from_mlp": false, "selected_threshold_high": 0.05, "selected_method_mode": "feature_first_selective_weighted_correction_v1", "winning_class_components": {"mlp_term": -0.1871271104140428, "feature_similarity_term": 0.3577134132385254, "feature_knn_term": 0.0, "graph_neighbor_term": 0.10899960818139655, "compatibility_term": 0.07111453405296635}}, {"node_id": 143, "mlp_pred": 3, "mlp_max_prob": 0.994838535785675, "mlp_margin": 0.9933030497049913, "was_uncertain": false, "final_pred": 3, "changed_from_mlp": false, "selected_threshold_high": 0.05, "selected_method_mode": "feature_first_selective_weighted_correction_v1", "winning_class_components": {"mlp_term": -0.005174830583939185, "feature_similarity_term": 0.30000135898590086, "feature_knn_term": 0.0, "graph_neighbor_term": 0.10899960818139655, "compatibility_term": 0.07111453405296635}}, {"node_id": 150, "mlp_pred": 3, "mlp_max_prob": 0.9890938997268677, "mlp_margin": 0.9862660686485469, "was_uncertain": false, "final_pred": 3, "changed_from_mlp": false, "selected_threshold_high": 0.05, "selected_method_mode": "feature_first_selective_weighted_correction_v1", "winning_class_components": {"mlp_term": -0.010966007754231098, "feature_similarity_term": 0.3000001788139343, "feature_knn_term": 0.0, "graph_neighbor_term": 0.039385323725843024, "compatibility_term": 0.05748427101170763}}, {"node_id": 151, "mlp_pred": 3, "mlp_max_prob": 0.7522844672203064, "mlp_margin": 0.624375507235527, "was_uncertain": false, "final_pred": 3, "changed_from_mlp": false, "selected_threshold_high": 0.05, "selected_method_mode": "feature_first_selective_weighted_correction_v1", "winning_class_components": {"mlp_term": -0.2846407456844031, "feature_similarity_term": 0.3, "feature_knn_term": 0.0, "graph_neighbor_term": 0.3333333333333333, "compatibility_term": 0.08490566037735849}}, {"node_id": 155, "mlp_pred": 3, "mlp_max_prob": 0.9992659687995911, "mlp_margin": 0.9989297647261992, "was_uncertain": false, "final_pred": 3, "changed_from_mlp": false, "selected_threshold_high": 0.05, "selected_method_mode": "feature_first_selective_weighted_correction_v1", "winning_class_components": {"mlp_term": -0.0007343007332155867, "feature_similarity_term": 0.30000168085098267, "feature_knn_term": 0.0, "graph_neighbor_term": 0.10899960818139655, "compatibility_term": 0.07111453405296635}}, {"node_id": 157, "mlp_pred": 3, "mlp_max_prob": 0.8294501304626465, "mlp_margin": 0.7381234541535378, "was_uncertain": false, "final_pred": 3, "changed_from_mlp": false, "selected_threshold_high": 0.05, "selected_method_mode": "feature_first_selective_weighted_correction_v1", "winning_class_components": {"mlp_term": -0.18699229115572685, "feature_similarity_term": 0.34683398008346555, "feature_knn_term": 0.0, "graph_neighbor_term": 0.0, "compatibility_term": 0.045283018867924525}}, {"node_id": 158, "mlp_pred": 0, "mlp_max_prob": 0.9400569796562195, "mlp_margin": 0.9186772629618645, "was_uncertain": false, "final_pred": 0, "changed_from_mlp": false, "selected_threshold_high": 0.05, "selected_method_mode": "feature_first_selective_weighted_correction_v1", "winning_class_components": {"mlp_term": -0.06181478889965006, "feature_similarity_term": 0.30000064373016355, "feature_knn_term": 0.0, "graph_neighbor_term": 0.0, "compatibility_term": 0.13}}, {"node_id": 164, "mlp_pred": 0, "mlp_max_prob": 0.9256417751312256, "mlp_margin": 0.8882942572236061, "was_uncertain": false, "final_pred": 0, "changed_from_mlp": false, "selected_threshold_high": 0.05, "selected_method_mode": "feature_first_selective_weighted_correction_v1", "winning_class_components": {"mlp_term": -0.07726797109258504, "feature_similarity_term": 0.32794965505599977, "feature_knn_term": 0.0, "graph_neighbor_term": 0.0, "compatibility_term": 0.11}}, {"node_id": 165, "mlp_pred": 3, "mlp_max_prob": 0.9987862706184387, "mlp_margin": 0.9984066548349801, "was_uncertain": false, "final_pred": 3, "changed_from_mlp": false, "selected_threshold_high": 0.05, "selected_method_mode": "feature_first_selective_weighted_correction_v1", "winning_class_components": {"mlp_term": -0.0012144665476075411, "feature_similarity_term": 0.3420961260795593, "feature_knn_term": 0.0, "graph_neighbor_term": 0.1974572411628505, "compatibility_term": 0.07239305226714039}}, {"node_id": 169, "mlp_pred": 2, "mlp_max_prob": 0.5021843314170837, "mlp_margin": 0.25936226546764374, "was_uncertain": false, "final_pred": 2, "changed_from_mlp": false, "selected_threshold_high": 0.05, "selected_method_mode": "feature_first_selective_weighted_correction_v1", "winning_class_components": {"mlp_term": -0.6887880326317116, "feature_similarity_term": 0.31835371255874634, "feature_knn_term": 0.0, "graph_neighbor_term": 0.15989089846042015, "compatibility_term": 0.06184190610716747}}, {"node_id": 172, "mlp_pred": 4, "mlp_max_prob": 0.38466498255729675, "mlp_margin": 0.02341863512992859, "was_uncertain": true, "final_pred": 0, "changed_from_mlp": true, "selected_threshold_high": 0.05, "selected_method_mode": "feature_first_selective_weighted_correction_v1", "winning_class_components": {"mlp_term": -1.0181951505343114, "feature_similarity_term": 0.3000004291534424, "feature_knn_term": 0.0, "graph_neighbor_term": 0.3079395374490945, "compatibility_term": 0.0443373465924018}}, {"node_id": 178, "mlp_pred": 3, "mlp_max_prob": 0.9005683064460754, "mlp_margin": 0.8377272933721542, "was_uncertain": false, "final_pred": 3, "changed_from_mlp": false, "selected_threshold_high": 0.05, "selected_method_mode": "feature_first_selective_weighted_correction_v1", "winning_class_components": {"mlp_term": -0.1047292633327549, "feature_similarity_term": 0.3000006079673767, "feature_knn_term": 0.0, "graph_neighbor_term": 0.0544998026695051, "compatibility_term": 0.05819877612364081}}]}